reactor/__init__.py
reactor/__main__.py
reactor/alerter.py
reactor/auth.py
reactor/cluster.py
reactor/config.py
reactor/console.py
reactor/enhancement.py
reactor/exceptions.py
reactor/init.py
reactor/kibana.py
reactor/loader.py
reactor/notifier.py
reactor/plugin.py
reactor/reactor.py
reactor/rule.py
reactor/util.py
reactor/validator.py
reactor/mappings/5/alert.json
reactor/mappings/5/error.json
reactor/mappings/5/settings.json
reactor/mappings/5/silence.json
reactor/mappings/5/status.json
reactor/mappings/6/alert.json
reactor/mappings/6/error.json
reactor/mappings/6/settings.json
reactor/mappings/6/silence.json
reactor/mappings/6/status.json
reactor/mappings/7/alert.json
reactor/mappings/7/error.json
reactor/mappings/7/settings.json
reactor/mappings/7/silence.json
reactor/mappings/7/status.json
reactor/schemas/alerter-command.yaml
reactor/schemas/alerter-debug.yaml
reactor/schemas/alerter-email.yaml
reactor/schemas/alerter-test.yaml
reactor/schemas/alerter-webhook.yaml
reactor/schemas/common.yaml
reactor/schemas/config.yaml
reactor/schemas/loader-file.yaml
reactor/schemas/ruletype-any.yaml
reactor/schemas/ruletype-blacklist.yaml
reactor/schemas/ruletype-cardinality.yaml
reactor/schemas/ruletype-change.yaml
reactor/schemas/ruletype-flatline.yaml
reactor/schemas/ruletype-frequency.yaml
reactor/schemas/ruletype-metric_aggregation.yaml
reactor/schemas/ruletype-new_term.yaml
reactor/schemas/ruletype-percentage_match.yaml
reactor/schemas/ruletype-spike.yaml
reactor/schemas/ruletype-spike_metric_aggregation.yaml
reactor/schemas/ruletype-whitelist.yaml
reactor/schemas/ruletype.yaml
ncc_reactor-1.2.9.dist-info/LICENSE
ncc_reactor-1.2.9.dist-info/METADATA
ncc_reactor-1.2.9.dist-info/WHEEL
ncc_reactor-1.2.9.dist-info/entry_points.txt
ncc_reactor-1.2.9.dist-info/top_level.txt
ncc_reactor-1.2.9.dist-info/RECORD
