Metadata-Version: 2.1
Name: ncc-reactor
Version: 1.2.9
Summary: Runs custom filters on Elasticsearch and alerts on matches
Home-page: https://nccgroup.com/
Author: Peter Scopes
Author-email: peter.scopes@nccgroup.com
Maintainer: Peter Scopes
Maintainer-email: peter.scopes@nccgroup.com
License: Copyright 2019 NCC Group
Keywords: alerting,alerts,elasticsearch,SIEM,scalable,reliable,modular
Platform: OS Independent
Classifier: Development Status :: 4 - Beta
Classifier: Environment :: Console
Classifier: Environment :: Console :: Curses
Classifier: Intended Audience :: Information Technology
Classifier: License :: Other/Proprietary License
Classifier: Natural Language :: English
Classifier: Operating System :: OS Independent
Classifier: Programming Language :: Python :: 3
Classifier: Topic :: Security
Requires-Python: >=3.6
Requires-Dist: apscheduler (>=3.6.0)
Requires-Dist: croniter (>=0.3.30)
Requires-Dist: elasticsearch (<8.0.0,>=6.0.0)
Requires-Dist: jsonschema (>=3.0.0)
Requires-Dist: prison (>=0.1.2)
Requires-Dist: python-dateutil (~=2.8.0)
Requires-Dist: pytz (>=2019.1)
Requires-Dist: PyYAML (>=5.1.1)
Requires-Dist: requests (>=2.0.0)
Requires-Dist: sortedcontainers (>=2.1.0)
Requires-Dist: texttable (>=1.0.0)
